snakemake_storage_plugin_fs/__init__.py
snakemake_storage_plugin_fs-1.1.2.dist-info/LICENSE
snakemake_storage_plugin_fs-1.1.2.dist-info/METADATA
snakemake_storage_plugin_fs-1.1.2.dist-info/WHEEL
snakemake_storage_plugin_fs-1.1.2.dist-info/RECORD
